{
  "scheme_id": "hdfc_equity_direct_growth",
  "scheme_name": "HDFC Equity Fund Direct Growth",
  "source_url": "https://groww.in/mutual-funds/hdfc-equity-fund-direct-growth",
  "content_captured_at": "2026-06-13",
  "scrape_run_id": "27460533349",
  "nav": {
    "display": "₹2,155.38",
    "amount_inr": 2155.38,
    "as_of_display": "12 Jun '26",
    "as_of_iso": "12 Jun '26"
  },
  "minimum_sip": {
    "display": "₹100",
    "amount_inr": 100.0
  },
  "fund_size_aum": {
    "display": "₹1,01,821.82 Cr",
    "amount_cr": 101821.82
  },
  "expense_ratio": {
    "display": "0.78%",
    "percent": 0.78
  },
  "rating": {
    "display": "5",
    "value": 5.0
  },
  "extraction_status": "complete",
  "missing_fields": [],
  "facts_hash": "4b1798431eb17ee31045d034fe3e99ac6d37cec840c80c5738d8c54487317e78"
}