{
  "scheme_id": "hdfc_elss_direct_growth",
  "scheme_name": "HDFC ELSS Tax Saver Fund Direct Plan Growth",
  "source_url": "https://groww.in/mutual-funds/hdfc-elss-tax-saver-fund-direct-plan-growth",
  "content_captured_at": "2026-06-16",
  "scrape_run_id": "27607036860",
  "nav": {
    "display": "₹1,459.51",
    "amount_inr": 1459.51,
    "as_of_display": "15 Jun '26",
    "as_of_iso": "15 Jun '26"
  },
  "minimum_sip": {
    "display": "₹500",
    "amount_inr": 500.0
  },
  "fund_size_aum": {
    "display": "₹15,366.50 Cr",
    "amount_cr": 15366.5
  },
  "expense_ratio": {
    "display": "1.17%",
    "percent": 1.17
  },
  "rating": {
    "display": "5",
    "value": 5.0
  },
  "extraction_status": "complete",
  "missing_fields": [],
  "facts_hash": "9904f49bf6c80affb0703f9f425389b3ead67fc43868fab255d34b171a13fbea"
}